{
"companyName": "DefaultCompany",
"productName": "TOC Assignment 5 Part B (Spr 2020)",
"productVersion": "0.1",
"dataUrl": "web_GL.data.unityweb",
"wasmCodeUrl": "web_GL.wasm.code.unityweb",
"wasmFrameworkUrl": "web_GL.wasm.framework.unityweb",
"graphicsAPI": ["WebGL 2.0"],
"webglContextAttributes": {"preserveDrawingBuffer": false},
"splashScreenStyle": "Dark",
"backgroundColor": "#0E0E0E",
"cacheControl": {"default": "must-revalidate"},
"developmentBuild": false,
"multithreading": false,
"unityVersion": "2019.3.9f1"
}